Metadata-Version: 2.1
Name: x3d
Version: 4.0.64.4
Summary: Python package support for Extensible 3D (X3D) Graphics International Standard (IS)
Home-page: https://www.web3d.org/x3d/stylesheets/python/python.html
Download-URL: https://www.web3d.org/x3d/stylesheets/python/x3d.py
Author: Don Brutzman
Author-email: Don Brutzman <brutzman@nps.edu>
Project-URL: Homepage, https://www.web3d.org/x3d/stylesheets/python/python.html
Keywords: X3D,3D,graphics,Web3D
Classifier: Programming Language :: Python :: 3
Classifier: License :: OSI Approved :: BSD License
Classifier: Operating System :: OS Independent
Requires-Python: >=3.1
License-File: LICENSE
License-File: license.html
License-File: license.txt
Requires-Dist: xmlschema
